data_loader/__init__.py
data_loader/blbr_trend_db.py
data_loader/mongodb_utils.py
data_loader/step_01_index_start.py
data_loader/step_01_start.py
data_loader/step_02_event_driven_trend.py
data_loader/step_03_sync_mongodb.py
data_loader/step_04_end.py
data_loader/utils.py
blbr_scripts-0.1.0.dist-info/METADATA
blbr_scripts-0.1.0.dist-info/WHEEL
blbr_scripts-0.1.0.dist-info/entry_points.txt
blbr_scripts-0.1.0.dist-info/top_level.txt
blbr_scripts-0.1.0.dist-info/RECORD
