Metadata-Version: 2.4
Name: blbr-scripts
Version: 0.1.0
Summary: BLBR Research Scripts for financial data analysis
Home-page: https://github.com/blbr-research/blbr-scripts
Author: BLBR Research Team
Author-email: info@blbr-research.com
Keywords: finance,trading,data analysis,stock market
Classifier: Development Status :: 3 - Alpha
Classifier: Intended Audience :: Financial and Insurance Industry
Classifier: Programming Language :: Python :: 3
Classifier: Programming Language :: Python :: 3.8
Classifier: Programming Language :: Python :: 3.9
Classifier: Programming Language :: Python :: 3.10
Classifier: Programming Language :: Python :: 3.11
Classifier: Topic :: Office/Business :: Financial :: Investment
Classifier: License :: OSI Approved :: MIT License
Requires-Python: >=3.8
Requires-Dist: appdirs==1.4.4
Requires-Dist: beautifulsoup4==4.9.3
Requires-Dist: certifi==2025.4.26
Requires-Dist: charset-normalizer==3.4.1
Requires-Dist: click==7.1.2
Requires-Dist: dnspython==2.7.0
Requires-Dist: dotenv==0.9.9
Requires-Dist: idna==3.10
Requires-Dist: jugaad-data==0.27
Requires-Dist: numpy==1.26.4
Requires-Dist: pandas>=2.2.0
Requires-Dist: psutil==7.0.0
Requires-Dist: pymongo==4.12.0
Requires-Dist: python-dateutil==2.9.0.post0
Requires-Dist: python-dotenv==1.1.0
Requires-Dist: pytz==2025.2
Requires-Dist: requests==2.32.3
Requires-Dist: six==1.17.0
Requires-Dist: soupsieve==2.7
Requires-Dist: tzdata==2025.2
Requires-Dist: urllib3==2.4.0
Requires-Dist: packaging==24.2
Requires-Dist: wheel==0.45.1
Requires-Dist: ta==0.11.0
Dynamic: author
Dynamic: author-email
Dynamic: classifier
Dynamic: description
Dynamic: description-content-type
Dynamic: home-page
Dynamic: keywords
Dynamic: requires-dist
Dynamic: requires-python
Dynamic: summary
